kcfg.py
kcfg-0.1.1.dist-info/entry_points.txt
kcfg-0.1.1.dist-info/LICENSE
kcfg-0.1.1.dist-info/WHEEL
kcfg-0.1.1.dist-info/METADATA
kcfg-0.1.1.dist-info/RECORD
