Metadata-Version: 2.1
Name: kcfg
Version: 0.1.1
Summary: Tool to read and write KDE INI config files, replaces kwriteconfig5 / kreadconfig5
Author-email: Aleksandar Radivojevic <rzhw3h@gmail.com>
Requires-Python: >=3.8.1
Classifier: Development Status :: 3 - Alpha
Classifier: Environment :: Console
Classifier: Topic :: Utilities
Classifier: Topic :: Desktop Environment
Classifier: License :: OSI Approved :: GNU General Public License v3 or later (GPLv3+)
Project-URL: Home, https://github.com/sandorex/kcfg
Project-URL: Tracker, https://github.com/sandorex/kcfg/issues
